peopleanalyticsdata/__init__.py
peopleanalyticsdata/peopleanalyticsdata.py
peopleanalyticsdata/data/charity_donation.csv
peopleanalyticsdata/data/employee_performance.csv
peopleanalyticsdata/data/employee_survey.csv
peopleanalyticsdata/data/graduates.csv
peopleanalyticsdata/data/health_insurance.csv
peopleanalyticsdata/data/job_retention.csv
peopleanalyticsdata/data/learning.csv
peopleanalyticsdata/data/managers.csv
peopleanalyticsdata/data/politics_survey.csv
peopleanalyticsdata/data/promotion.csv
peopleanalyticsdata/data/recruiting.csv
peopleanalyticsdata/data/salespeople.csv
peopleanalyticsdata/data/soccer.csv
peopleanalyticsdata/data/sociological_data.csv
peopleanalyticsdata/data/speed_dating.csv
peopleanalyticsdata/data/ugtests.csv
tests/__init__.py
tests/test_peopleanalyticsdata.py
tests/.ipynb_checkpoints/test_peopleanalyticsdata-checkpoint.py
peopleanalyticsdata-0.1.5.dist-info/LICENSE
peopleanalyticsdata-0.1.5.dist-info/METADATA
peopleanalyticsdata-0.1.5.dist-info/WHEEL
peopleanalyticsdata-0.1.5.dist-info/top_level.txt
peopleanalyticsdata-0.1.5.dist-info/RECORD
