Metadata-Version: 2.1
Name: peopleanalyticsdata
Version: 0.1.5
Summary: Allows data access from the book - Handbook of Regression Modeling in People Analytics.
Home-page: https://github.com/akshayreddykotha/peopleanalyticsdata
Author: Akshay Kotha
Author-email: akotha@ucsd.edu
License: UNKNOWN
Platform: UNKNOWN
Classifier: Programming Language :: Python
Classifier: Programming Language :: Python :: 3
Classifier: Programming Language :: Python :: 3.6
